[
    {
        "label": "apple",
        "point": [
            170.5,
            184.0
        ],
        "radius": 1.500100016593933
    },
    {
        "label": "apple",
        "point": [
            222.5,
            183.5
        ],
        "radius": 1.581238865852356
    },
    {
        "label": "apple",
        "point": [
            180.0,
            184.0
        ],
        "radius": 2.0000998973846436
    },
    {
        "label": "apple",
        "point": [
            237.5,
            183.0
        ],
        "radius": 1.1181340217590332
    },
    {
        "label": "apple",
        "point": [
            266.5,
            182.5
        ],
        "radius": 2.9155757427215576
    },
    {
        "label": "apple",
        "point": [
            128.0,
            181.5
        ],
        "radius": 3.201662063598633
    },
    {
        "label": "apple",
        "point": [
            243.5,
            179.0
        ],
        "radius": 2.6926822662353516
    },
    {
        "label": "apple",
        "point": [
            187.0,
            180.5
        ],
        "radius": 4.717090606689453
    },
    {
        "label": "apple",
        "point": [
            156.0,
            178.0
        ],
        "radius": 1.000100016593933
    },
    {
        "label": "apple",
        "point": [
            113.5,
            181.0
        ],
        "radius": 4.609872341156006
    },
    {
        "label": "apple",
        "point": [
            98.0,
            180.5
        ],
        "radius": 2.6926822662353516
    },
    {
        "label": "apple",
        "point": [
            155.5,
            182.5
        ],
        "radius": 8.631438255310059
    },
    {
        "label": "apple",
        "point": [
            125.5,
            178.0
        ],
        "radius": 1.1181340217590332
    },
    {
        "label": "apple",
        "point": [
            175.9166717529297,
            179.72222900390625
        ],
        "radius": 4.278682231903076
    },
    {
        "label": "apple",
        "point": [
            19.214284896850586,
            176.35714721679688
        ],
        "radius": 1.8211801052093506
    },
    {
        "label": "apple",
        "point": [
            187.0,
            174.0
        ],
        "radius": 1.000100016593933
    },
    {
        "label": "apple",
        "point": [
            179.5,
            174.5
        ],
        "radius": 1.581238865852356
    },
    {
        "label": "apple",
        "point": [
            83.0,
            175.0
        ],
        "radius": 1.000100016593933
    },
    {
        "label": "apple",
        "point": [
            74.0,
            177.0
        ],
        "radius": 3.1623775959014893
    },
    {
        "label": "apple",
        "point": [
            69.5,
            175.8333282470703
        ],
        "radius": 1.9003955125808716
    },
    {
        "label": "apple",
        "point": [
            46.19620132446289,
            180.3607635498047
        ],
        "radius": 8.610755920410156
    },
    {
        "label": "apple",
        "point": [
            208.0,
            176.5
        ],
        "radius": 7.826338291168213
    },
    {
        "label": "apple",
        "point": [
            145.0,
            173.5
        ],
        "radius": 4.272101879119873
    },
    {
        "label": "apple",
        "point": [
            173.5,
            171.0
        ],
        "radius": 1.8028756380081177
    },
    {
        "label": "apple",
        "point": [
            114.0,
            170.5
        ],
        "radius": 1.1181340217590332
    },
    {
        "label": "apple",
        "point": [
            137.6999969482422,
            170.3000030517578
        ],
        "radius": 1.838581919670105
    },
    {
        "label": "apple",
        "point": [
            71.0,
            170.0
        ],
        "radius": 1.000100016593933
    },
    {
        "label": "apple",
        "point": [
            46.5,
            170.0
        ],
        "radius": 1.1181340217590332
    },
    {
        "label": "apple",
        "point": [
            227.0,
            173.0
        ],
        "radius": 5.385264873504639
    },
    {
        "label": "apple",
        "point": [
            120.859375,
            173.09375
        ],
        "radius": 5.219995975494385
    },
    {
        "label": "apple",
        "point": [
            219.5,
            169.0
        ],
        "radius": 2.061652660369873
    },
    {
        "label": "apple",
        "point": [
            132.0,
            168.0
        ],
        "radius": 1.414313554763794
    },
    {
        "label": "apple",
        "point": [
            89.0,
            167.5
        ],
        "radius": 1.1181340217590332
    },
    {
        "label": "apple",
        "point": [
            243.0,
            167.0
        ],
        "radius": 1.414313554763794
    },
    {
        "label": "apple",
        "point": [
            74.0,
            165.0
        ],
        "radius": 1.000100016593933
    },
    {
        "label": "apple",
        "point": [
            58.5,
            169.5
        ],
        "radius": 8.631438255310059
    },
    {
        "label": "apple",
        "point": [
            210.5,
            167.5
        ],
        "radius": 3.5356338024139404
    },
    {
        "label": "apple",
        "point": [
            204.5,
            164.0
        ],
        "radius": 1.500100016593933
    },
    {
        "label": "apple",
        "point": [
            196.0,
            163.5
        ],
        "radius": 2.061652660369873
    },
    {
        "label": "apple",
        "point": [
            157.0,
            165.5
        ],
        "radius": 7.43313455581665
    },
    {
        "label": "apple",
        "point": [
            83.08064270019531,
            166.40322875976562
        ],
        "radius": 3.9072558879852295
    },
    {
        "label": "apple",
        "point": [
            44.0,
            164.5
        ],
        "radius": 1.500100016593933
    },
    {
        "label": "apple",
        "point": [
            35.41752624511719,
            169.79896545410156
        ],
        "radius": 6.823972702026367
    },
    {
        "label": "apple",
        "point": [
            262.6666564941406,
            162.0
        ],
        "radius": 1.6667747497558594
    },
    {
        "label": "apple",
        "point": [
            85.0,
            161.0
        ],
        "radius": 1.000100016593933
    },
    {
        "label": "apple",
        "point": [
            136.0,
            161.0
        ],
        "radius": 6.082862854003906
    },
    {
        "label": "apple",
        "point": [
            117.5,
            164.0
        ],
        "radius": 4.717090606689453
    },
    {
        "label": "apple",
        "point": [
            179.5,
            160.5
        ],
        "radius": 3.5356338024139404
    },
    {
        "label": "apple",
        "point": [
            68.90908813476562,
            162.72727966308594
        ],
        "radius": 4.273801803588867
    },
    {
        "label": "apple",
        "point": [
            190.5,
            159.0
        ],
        "radius": 1.8028756380081177
    },
    {
        "label": "apple",
        "point": [
            121.0,
            159.0
        ],
        "radius": 1.414313554763794
    },
    {
        "label": "apple",
        "point": [
            4.5,
            162.0
        ],
        "radius": 4.609872341156006
    },
    {
        "label": "apple",
        "point": [
            251.7857208251953,
            161.64285278320312
        ],
        "radius": 7.399072170257568
    },
    {
        "label": "apple",
        "point": [
            197.75,
            159.75
        ],
        "radius": 3.952946901321411
    },
    {
        "label": "apple",
        "point": [
            154.5,
            157.0
        ],
        "radius": 1.8028756380081177
    },
    {
        "label": "apple",
        "point": [
            139.8333282470703,
            157.5
        ],
        "radius": 3.2060022354125977
    },
    {
        "label": "apple",
        "point": [
            123.0,
            156.0
        ],
        "radius": 1.000100016593933
    },
    {
        "label": "apple",
        "point": [
            135.0,
            156.0
        ],
        "radius": 2.0000998973846436
    },
    {
        "label": "apple",
        "point": [
            127.40908813476562,
            154.9545440673828
        ],
        "radius": 2.5914103984832764
    },
    {
        "label": "apple",
        "point": [
            236.93878173828125,
            165.051025390625
        ],
        "radius": 15.620795249938965
    },
    {
        "label": "apple",
        "point": [
            211.31817626953125,
            156.68182373046875
        ],
        "radius": 4.0478596687316895
    },
    {
        "label": "apple",
        "point": [
            171.89999389648438,
            155.10000610351562
        ],
        "radius": 2.1024858951568604
    },
    {
        "label": "apple",
        "point": [
            161.7058868408203,
            156.05882263183594
        ],
        "radius": 3.8236258029937744
    },
    {
        "label": "apple",
        "point": [
            131.0,
            153.5
        ],
        "radius": 1.1181340217590332
    },
    {
        "label": "apple",
        "point": [
            59.5,
            157.0
        ],
        "radius": 7.632268905639648
    },
    {
        "label": "apple",
        "point": [
            149.5,
            153.0
        ],
        "radius": 1.1181340217590332
    },
    {
        "label": "apple",
        "point": [
            239.0,
            153.0
        ],
        "radius": 5.099119663238525
    },
    {
        "label": "apple",
        "point": [
            267.0,
            151.25
        ],
        "radius": 2.0156643390655518
    },
    {
        "label": "apple",
        "point": [
            145.35293579101562,
            155.23529052734375
        ],
        "radius": 5.407393455505371
    },
    {
        "label": "apple",
        "point": [
            70.16666412353516,
            152.5
        ],
        "radius": 2.6353321075439453
    },
    {
        "label": "apple",
        "point": [
            254.0,
            149.5
        ],
        "radius": 1.1181340217590332
    },
    {
        "label": "apple",
        "point": [
            35.0,
            163.5
        ],
        "radius": 16.919023513793945
    },
    {
        "label": "apple",
        "point": [
            56.5,
            148.5
        ],
        "radius": 1.581238865852356
    },
    {
        "label": "apple",
        "point": [
            222.0,
            148.0
        ],
        "radius": 1.000100016593933
    },
    {
        "label": "apple",
        "point": [
            182.5,
            150.0
        ],
        "radius": 6.576573371887207
    },
    {
        "label": "apple",
        "point": [
            161.0,
            149.0
        ],
        "radius": 2.2361679077148438
    },
    {
        "label": "apple",
        "point": [
            20.5,
            147.5
        ],
        "radius": 1.581238865852356
    },
    {
        "label": "apple",
        "point": [
            10.5,
            148.5
        ],
        "radius": 2.12142014503479
    },
    {
        "label": "apple",
        "point": [
            250.5,
            147.5
        ],
        "radius": 1.581238865852356
    },
    {
        "label": "apple",
        "point": [
            189.5,
            147.5
        ],
        "radius": 1.581238865852356
    },
    {
        "label": "apple",
        "point": [
            168.0,
            146.5
        ],
        "radius": 1.1181340217590332
    },
    {
        "label": "apple",
        "point": [
            87.0,
            146.0
        ],
        "radius": 1.000100016593933
    },
    {
        "label": "apple",
        "point": [
            52.5,
            147.0
        ],
        "radius": 1.500100016593933
    },
    {
        "label": "apple",
        "point": [
            227.19564819335938,
            147.97825622558594
        ],
        "radius": 2.984785556793213
    },
    {
        "label": "apple",
        "point": [
            218.5,
            147.0
        ],
        "radius": 2.061652660369873
    },
    {
        "label": "apple",
        "point": [
            184.0,
            145.6666717529297
        ],
        "radius": 1.6667625904083252
    },
    {
        "label": "apple",
        "point": [
            167.0,
            144.5
        ],
        "radius": 1.1181340217590332
    },
    {
        "label": "apple",
        "point": [
            59.5,
            145.5
        ],
        "radius": 2.549609661102295
    },
    {
        "label": "apple",
        "point": [
            44.5,
            145.0
        ],
        "radius": 1.1181340217590332
    },
    {
        "label": "apple",
        "point": [
            246.0,
            143.5
        ],
        "radius": 1.1181340217590332
    },
    {
        "label": "apple",
        "point": [
            173.0,
            145.0
        ],
        "radius": 2.2361679077148438
    },
    {
        "label": "apple",
        "point": [
            111.5,
            142.0
        ],
        "radius": 6.576573371887207
    },
    {
        "label": "apple",
        "point": [
            167.0,
            139.5
        ],
        "radius": 2.5000998973846436
    },
    {
        "label": "apple",
        "point": [
            3.3709676265716553,
            145.18386840820312
        ],
        "radius": 7.935553073883057
    },
    {
        "label": "apple",
        "point": [
            205.42857360839844,
            145.30357360839844
        ],
        "radius": 8.425660133361816
    },
    {
        "label": "apple",
        "point": [
            50.0,
            141.0
        ],
        "radius": 4.472236156463623
    },
    {
        "label": "apple",
        "point": [
            218.5,
            139.5
        ],
        "radius": 3.5356338024139404
    },
    {
        "label": "apple",
        "point": [
            151.0,
            142.5
        ],
        "radius": 8.732224464416504
    },
    {
        "label": "apple",
        "point": [
            122.0,
            137.5
        ],
        "radius": 2.061652660369873
    },
    {
        "label": "apple",
        "point": [
            231.5,
            137.5
        ],
        "radius": 6.5193023681640625
    },
    {
        "label": "apple",
        "point": [
            99.0,
            137.5
        ],
        "radius": 2.5000998973846436
    },
    {
        "label": "apple",
        "point": [
            243.21697998046875,
            136.27359008789062
        ],
        "radius": 4.790938377380371
    },
    {
        "label": "apple",
        "point": [
            235.0,
            134.5
        ],
        "radius": 2.061652660369873
    },
    {
        "label": "apple",
        "point": [
            26.363014221191406,
            141.1643829345703
        ],
        "radius": 8.638649940490723
    },
    {
        "label": "apple",
        "point": [
            93.0,
            135.0
        ],
        "radius": 2.2361679077148438
    },
    {
        "label": "apple",
        "point": [
            50.0,
            133.5
        ],
        "radius": 1.8028756380081177
    },
    {
        "label": "apple",
        "point": [
            229.64285278320312,
            132.7857208251953
        ],
        "radius": 1.821177363395691
    },
    {
        "label": "apple",
        "point": [
            209.0,
            131.0
        ],
        "radius": 2.2361679077148438
    },
    {
        "label": "apple",
        "point": [
            147.0,
            132.0
        ],
        "radius": 2.2361679077148438
    },
    {
        "label": "apple",
        "point": [
            192.30487060546875,
            139.0853729248047
        ],
        "radius": 10.345489501953125
    },
    {
        "label": "apple",
        "point": [
            161.5,
            130.0
        ],
        "radius": 1.1181340217590332
    },
    {
        "label": "apple",
        "point": [
            180.39854431152344,
            130.55796813964844
        ],
        "radius": 5.618969917297363
    },
    {
        "label": "apple",
        "point": [
            165.75,
            129.75
        ],
        "radius": 2.850538492202759
    },
    {
        "label": "apple",
        "point": [
            216.0,
            127.0
        ],
        "radius": 1.414313554763794
    },
    {
        "label": "apple",
        "point": [
            152.25,
            128.0
        ],
        "radius": 3.7500998973846436
    },
    {
        "label": "apple",
        "point": [
            114.5,
            131.0
        ],
        "radius": 7.762187480926514
    },
    {
        "label": "apple",
        "point": [
            234.5,
            125.5
        ],
        "radius": 2.12142014503479
    },
    {
        "label": "apple",
        "point": [
            147.0,
            124.5
        ],
        "radius": 1.1181340217590332
    },
    {
        "label": "apple",
        "point": [
            55.35714340209961,
            126.64286041259766
        ],
        "radius": 2.7200191020965576
    },
    {
        "label": "apple",
        "point": [
            43.0,
            125.5
        ],
        "radius": 2.6926822662353516
    },
    {
        "label": "apple",
        "point": [
            102.0,
            125.5
        ],
        "radius": 4.609872341156006
    },
    {
        "label": "apple",
        "point": [
            228.8333282470703,
            123.0
        ],
        "radius": 2.166771650314331
    },
    {
        "label": "apple",
        "point": [
            190.7857208251953,
            122.78571319580078
        ],
        "radius": 2.5254759788513184
    },
    {
        "label": "apple",
        "point": [
            183.5,
            123.0
        ],
        "radius": 2.061652660369873
    },
    {
        "label": "apple",
        "point": [
            151.0,
            121.0
        ],
        "radius": 1.000100016593933
    },
    {
        "label": "apple",
        "point": [
            130.22909545898438,
            134.2600555419922
        ],
        "radius": 16.74161148071289
    },
    {
        "label": "apple",
        "point": [
            47.0,
            120.5
        ],
        "radius": 1.1181340217590332
    },
    {
        "label": "apple",
        "point": [
            253.0,
            120.0
        ],
        "radius": 1.414313554763794
    },
    {
        "label": "apple",
        "point": [
            219.35714721679688,
            121.64286041259766
        ],
        "radius": 2.720015287399292
    },
    {
        "label": "apple",
        "point": [
            118.5,
            120.0
        ],
        "radius": 1.1181340217590332
    },
    {
        "label": "apple",
        "point": [
            268.5,
            119.5
        ],
        "radius": 1.581238865852356
    },
    {
        "label": "apple",
        "point": [
            173.5,
            117.5
        ],
        "radius": 1.581238865852356
    },
    {
        "label": "apple",
        "point": [
            88.50746154785156,
            142.97015380859375
        ],
        "radius": 33.04739761352539
    },
    {
        "label": "apple",
        "point": [
            53.0,
            117.0
        ],
        "radius": 3.1623775959014893
    },
    {
        "label": "apple",
        "point": [
            162.31817626953125,
            117.5
        ],
        "radius": 5.876588821411133
    },
    {
        "label": "apple",
        "point": [
            128.5,
            117.0
        ],
        "radius": 4.031229019165039
    },
    {
        "label": "apple",
        "point": [
            175.0,
            113.0
        ],
        "radius": 3.0000998973846436
    },
    {
        "label": "apple",
        "point": [
            103.0,
            113.33333587646484
        ],
        "radius": 1.6667686700820923
    },
    {
        "label": "apple",
        "point": [
            73.5,
            112.5
        ],
        "radius": 1.581238865852356
    },
    {
        "label": "apple",
        "point": [
            47.0,
            114.0
        ],
        "radius": 2.8285269737243652
    },
    {
        "label": "apple",
        "point": [
            266.8333435058594,
            112.83333587646484
        ],
        "radius": 2.173156976699829
    },
    {
        "label": "apple",
        "point": [
            110.57546997070312,
            116.14151000976562
        ],
        "radius": 8.501614570617676
    },
    {
        "label": "apple",
        "point": [
            107.0,
            112.0
        ],
        "radius": 1.414313554763794
    },
    {
        "label": "apple",
        "point": [
            67.5,
            114.0
        ],
        "radius": 3.9052248001098633
    },
    {
        "label": "apple",
        "point": [
            225.36207580566406,
            113.39655303955078
        ],
        "radius": 3.6595733165740967
    },
    {
        "label": "apple",
        "point": [
            144.5,
            109.5
        ],
        "radius": 1.581238865852356
    },
    {
        "label": "apple",
        "point": [
            183.5,
            109.5
        ],
        "radius": 1.581238865852356
    },
    {
        "label": "apple",
        "point": [
            58.0,
            109.5
        ],
        "radius": 1.500100016593933
    },
    {
        "label": "apple",
        "point": [
            56.0,
            110.5
        ],
        "radius": 2.6926822662353516
    },
    {
        "label": "apple",
        "point": [
            258.0,
            108.0
        ],
        "radius": 1.414313554763794
    },
    {
        "label": "apple",
        "point": [
            247.0833282470703,
            114.70833587646484
        ],
        "radius": 11.049631118774414
    },
    {
        "label": "apple",
        "point": [
            40.0,
            110.5
        ],
        "radius": 4.031229019165039
    },
    {
        "label": "apple",
        "point": [
            179.3000030517578,
            107.69999694824219
        ],
        "radius": 1.838573694229126
    },
    {
        "label": "apple",
        "point": [
            112.35713958740234,
            107.21428680419922
        ],
        "radius": 1.8211809396743774
    },
    {
        "label": "apple",
        "point": [
            103.16666412353516,
            107.16666412353516
        ],
        "radius": 1.1786149740219116
    },
    {
        "label": "apple",
        "point": [
            49.21428680419922,
            107.64286041259766
        ],
        "radius": 1.8211767673492432
    },
    {
        "label": "apple",
        "point": [
            265.0,
            106.0
        ],
        "radius": 1.000100016593933
    },
    {
        "label": "apple",
        "point": [
            241.0,
            105.0
        ],
        "radius": 1.000100016593933
    },
    {
        "label": "apple",
        "point": [
            137.5,
            106.0
        ],
        "radius": 4.031229019165039
    },
    {
        "label": "apple",
        "point": [
            245.0,
            103.0
        ],
        "radius": 5.099119663238525
    },
    {
        "label": "apple",
        "point": [
            173.0,
            105.0
        ],
        "radius": 3.6056511402130127
    },
    {
        "label": "apple",
        "point": [
            55.5,
            104.0
        ],
        "radius": 2.061652660369873
    },
    {
        "label": "apple",
        "point": [
            32.21428680419922,
            112.35713958740234
        ],
        "radius": 12.324376106262207
    },
    {
        "label": "apple",
        "point": [
            233.5,
            102.5
        ],
        "radius": 5.147915363311768
    },
    {
        "label": "apple",
        "point": [
            42.0,
            102.5
        ],
        "radius": 3.3542017936706543
    },
    {
        "label": "apple",
        "point": [
            268.5,
            100.0
        ],
        "radius": 1.1181340217590332
    },
    {
        "label": "apple",
        "point": [
            262.0,
            100.33333587646484
        ],
        "radius": 1.6667686700820923
    },
    {
        "label": "apple",
        "point": [
            132.0,
            99.5
        ],
        "radius": 1.1181340217590332
    },
    {
        "label": "apple",
        "point": [
            0.5,
            100.0
        ],
        "radius": 2.061652660369873
    },
    {
        "label": "apple",
        "point": [
            88.0,
            97.5
        ],
        "radius": 1.1181340217590332
    },
    {
        "label": "apple",
        "point": [
            192.125,
            98.0
        ],
        "radius": 6.206195831298828
    },
    {
        "label": "apple",
        "point": [
            105.0,
            108.5
        ],
        "radius": 28.11148452758789
    },
    {
        "label": "apple",
        "point": [
            265.5,
            96.0
        ],
        "radius": 3.6401548385620117
    },
    {
        "label": "apple",
        "point": [
            158.0,
            94.5
        ],
        "radius": 1.1181340217590332
    },
    {
        "label": "apple",
        "point": [
            254.875,
            95.5
        ],
        "radius": 4.155292510986328
    },
    {
        "label": "apple",
        "point": [
            183.5,
            94.0
        ],
        "radius": 1.1181340217590332
    },
    {
        "label": "apple",
        "point": [
            61.0,
            98.5
        ],
        "radius": 6.800835609436035
    },
    {
        "label": "apple",
        "point": [
            243.6666717529297,
            95.0
        ],
        "radius": 4.772702217102051
    },
    {
        "label": "apple",
        "point": [
            56.0,
            93.5
        ],
        "radius": 2.6926822662353516
    },
    {
        "label": "apple",
        "point": [
            195.86585998535156,
            106.6463394165039
        ],
        "radius": 24.41913414001465
    },
    {
        "label": "apple",
        "point": [
            115.0,
            92.0
        ],
        "radius": 4.123205661773682
    },
    {
        "label": "apple",
        "point": [
            2.0,
            89.5
        ],
        "radius": 2.061652660369873
    },
    {
        "label": "apple",
        "point": [
            268.5,
            89.5
        ],
        "radius": 1.581238865852356
    },
    {
        "label": "apple",
        "point": [
            249.5,
            89.0
        ],
        "radius": 1.1181340217590332
    },
    {
        "label": "apple",
        "point": [
            61.5,
            88.0
        ],
        "radius": 1.500100016593933
    },
    {
        "label": "apple",
        "point": [
            107.0,
            88.5
        ],
        "radius": 1.8028756380081177
    },
    {
        "label": "apple",
        "point": [
            171.5,
            93.0
        ],
        "radius": 7.43313455581665
    },
    {
        "label": "apple",
        "point": [
            166.5,
            87.5
        ],
        "radius": 1.581238865852356
    },
    {
        "label": "apple",
        "point": [
            0.0,
            87.0
        ],
        "radius": 1.000100016593933
    },
    {
        "label": "apple",
        "point": [
            123.0,
            86.0
        ],
        "radius": 1.000100016593933
    },
    {
        "label": "apple",
        "point": [
            15.5,
            87.0
        ],
        "radius": 2.061652660369873
    },
    {
        "label": "apple",
        "point": [
            176.5,
            85.5
        ],
        "radius": 1.581238865852356
    },
    {
        "label": "apple",
        "point": [
            243.5,
            84.75
        ],
        "radius": 2.304986000061035
    },
    {
        "label": "apple",
        "point": [
            235.5,
            83.0
        ],
        "radius": 1.500100016593933
    },
    {
        "label": "apple",
        "point": [
            93.0,
            88.5
        ],
        "radius": 6.800835609436035
    },
    {
        "label": "apple",
        "point": [
            72.25,
            98.0
        ],
        "radius": 15.052093505859375
    },
    {
        "label": "apple",
        "point": [
            49.5,
            88.0
        ],
        "radius": 5.315173149108887
    },
    {
        "label": "apple",
        "point": [
            7.611111164093018,
            86.61111450195312
        ],
        "radius": 3.6625521183013916
    },
    {
        "label": "apple",
        "point": [
            58.0,
            83.0
        ],
        "radius": 2.0000998973846436
    },
    {
        "label": "apple",
        "point": [
            97.5,
            80.5
        ],
        "radius": 1.581238865852356
    },
    {
        "label": "apple",
        "point": [
            51.0,
            81.0
        ],
        "radius": 2.2361679077148438
    },
    {
        "label": "apple",
        "point": [
            217.5,
            93.0
        ],
        "radius": 22.610937118530273
    },
    {
        "label": "apple",
        "point": [
            68.5,
            79.5
        ],
        "radius": 2.549609661102295
    },
    {
        "label": "apple",
        "point": [
            19.5,
            106.5
        ],
        "radius": 34.532691955566406
    },
    {
        "label": "apple",
        "point": [
            246.0,
            77.5
        ],
        "radius": 1.1181340217590332
    },
    {
        "label": "apple",
        "point": [
            100.95454406738281,
            78.40908813476562
        ],
        "radius": 2.5914103984832764
    },
    {
        "label": "apple",
        "point": [
            58.5,
            77.5
        ],
        "radius": 1.581238865852356
    },
    {
        "label": "apple",
        "point": [
            27.5,
            78.5
        ],
        "radius": 2.9155757427215576
    },
    {
        "label": "apple",
        "point": [
            155.5,
            79.5
        ],
        "radius": 8.276573181152344
    },
    {
        "label": "apple",
        "point": [
            85.0,
            77.5
        ],
        "radius": 6.18475866317749
    },
    {
        "label": "apple",
        "point": [
            66.5,
            74.5
        ],
        "radius": 1.581238865852356
    },
    {
        "label": "apple",
        "point": [
            4.5,
            76.0
        ],
        "radius": 2.6926822662353516
    },
    {
        "label": "apple",
        "point": [
            141.10606384277344,
            89.10606384277344
        ],
        "radius": 16.36408233642578
    },
    {
        "label": "apple",
        "point": [
            140.5,
            73.5
        ],
        "radius": 1.581238865852356
    },
    {
        "label": "apple",
        "point": [
            24.0,
            73.5
        ],
        "radius": 3.3542017936706543
    },
    {
        "label": "apple",
        "point": [
            14.642857551574707,
            76.64286041259766
        ],
        "radius": 4.656673908233643
    },
    {
        "label": "apple",
        "point": [
            87.0,
            71.5
        ],
        "radius": 3.0414812564849854
    },
    {
        "label": "apple",
        "point": [
            203.5,
            74.25
        ],
        "radius": 4.5070390701293945
    },
    {
        "label": "apple",
        "point": [
            163.0,
            71.0
        ],
        "radius": 1.000100016593933
    },
    {
        "label": "apple",
        "point": [
            67.0,
            70.0
        ],
        "radius": 1.000100016593933
    },
    {
        "label": "apple",
        "point": [
            269.0,
            69.0
        ],
        "radius": 1.000100016593933
    },
    {
        "label": "apple",
        "point": [
            214.0,
            69.0
        ],
        "radius": 2.0000998973846436
    },
    {
        "label": "apple",
        "point": [
            122.5,
            73.5
        ],
        "radius": 9.192488670349121
    },
    {
        "label": "apple",
        "point": [
            102.5,
            70.0
        ],
        "radius": 2.061652660369873
    },
    {
        "label": "apple",
        "point": [
            98.0,
            71.5
        ],
        "radius": 4.031229019165039
    },
    {
        "label": "apple",
        "point": [
            38.5,
            67.0
        ],
        "radius": 1.500100016593933
    },
    {
        "label": "apple",
        "point": [
            20.5,
            67.0
        ],
        "radius": 1.1181340217590332
    },
    {
        "label": "apple",
        "point": [
            258.5,
            66.5
        ],
        "radius": 2.9155757427215576
    },
    {
        "label": "apple",
        "point": [
            76.5,
            70.0
        ],
        "radius": 6.020897388458252
    },
    {
        "label": "apple",
        "point": [
            235.0,
            67.0
        ],
        "radius": 6.000100135803223
    },
    {
        "label": "apple",
        "point": [
            82.0,
            64.5
        ],
        "radius": 1.1181340217590332
    },
    {
        "label": "apple",
        "point": [
            237.5,
            63.0
        ],
        "radius": 1.1181340217590332
    },
    {
        "label": "apple",
        "point": [
            95.0,
            63.5
        ],
        "radius": 1.8028756380081177
    },
    {
        "label": "apple",
        "point": [
            91.0,
            63.0
        ],
        "radius": 1.414313554763794
    },
    {
        "label": "apple",
        "point": [
            132.0,
            61.5
        ],
        "radius": 2.061652660369873
    },
    {
        "label": "apple",
        "point": [
            238.5,
            60.5
        ],
        "radius": 1.581238865852356
    },
    {
        "label": "apple",
        "point": [
            220.1666717529297,
            61.16666793823242
        ],
        "radius": 1.1786068677902222
    },
    {
        "label": "apple",
        "point": [
            183.30435180664062,
            77.08695983886719
        ],
        "radius": 17.403623580932617
    },
    {
        "label": "apple",
        "point": [
            113.5,
            65.0
        ],
        "radius": 9.552586555480957
    },
    {
        "label": "apple",
        "point": [
            61.0,
            63.5
        ],
        "radius": 5.02503776550293
    },
    {
        "label": "apple",
        "point": [
            19.5,
            60.5
        ],
        "radius": 2.549609661102295
    },
    {
        "label": "apple",
        "point": [
            162.5,
            62.0
        ],
        "radius": 5.4084272384643555
    },
    {
        "label": "apple",
        "point": [
            38.20000076293945,
            61.0
        ],
        "radius": 5.200099468231201
    },
    {
        "label": "apple",
        "point": [
            7.357142925262451,
            62.35714340209961
        ],
        "radius": 6.367267608642578
    },
    {
        "label": "apple",
        "point": [
            203.5,
            59.5
        ],
        "radius": 8.631438255310059
    },
    {
        "label": "apple",
        "point": [
            170.0,
            58.5
        ],
        "radius": 5.2202534675598145
    },
    {
        "label": "apple",
        "point": [
            129.5,
            57.5
        ],
        "radius": 1.581238865852356
    },
    {
        "label": "apple",
        "point": [
            98.0,
            57.0
        ],
        "radius": 2.2361679077148438
    },
    {
        "label": "apple",
        "point": [
            226.5,
            57.0
        ],
        "radius": 2.5000998973846436
    },
    {
        "label": "apple",
        "point": [
            59.0,
            56.0
        ],
        "radius": 3.1623775959014893
    },
    {
        "label": "apple",
        "point": [
            51.5,
            57.0
        ],
        "radius": 2.5000998973846436
    },
    {
        "label": "apple",
        "point": [
            2.0,
            55.5
        ],
        "radius": 1.1181340217590332
    },
    {
        "label": "apple",
        "point": [
            110.0,
            55.5
        ],
        "radius": 4.031229019165039
    },
    {
        "label": "apple",
        "point": [
            209.5,
            53.5
        ],
        "radius": 1.581238865852356
    },
    {
        "label": "apple",
        "point": [
            149.0,
            62.5
        ],
        "radius": 14.430970191955566
    },
    {
        "label": "apple",
        "point": [
            184.0,
            56.5
        ],
        "radius": 8.732224464416504
    },
    {
        "label": "apple",
        "point": [
            140.0,
            52.5
        ],
        "radius": 1.1181340217590332
    },
    {
        "label": "apple",
        "point": [
            79.98648834228516,
            53.85135269165039
        ],
        "radius": 4.148769378662109
    },
    {
        "label": "apple",
        "point": [
            50.5,
            50.5
        ],
        "radius": 2.549609661102295
    },
    {
        "label": "apple",
        "point": [
            14.5,
            50.5
        ],
        "radius": 2.549609661102295
    },
    {
        "label": "apple",
        "point": [
            64.0,
            51.0
        ],
        "radius": 2.2361679077148438
    },
    {
        "label": "apple",
        "point": [
            258.0,
            49.0
        ],
        "radius": 1.000100016593933
    },
    {
        "label": "apple",
        "point": [
            248.0,
            51.0
        ],
        "radius": 8.544103622436523
    },
    {
        "label": "apple",
        "point": [
            111.5999984741211,
            54.0
        ],
        "radius": 7.665608882904053
    },
    {
        "label": "apple",
        "point": [
            235.0,
            48.5
        ],
        "radius": 4.272101879119873
    },
    {
        "label": "apple",
        "point": [
            74.0,
            49.5
        ],
        "radius": 2.6926822662353516
    },
    {
        "label": "apple",
        "point": [
            98.0,
            47.0
        ],
        "radius": 1.414313554763794
    },
    {
        "label": "apple",
        "point": [
            233.0,
            45.0
        ],
        "radius": 1.414313554763794
    },
    {
        "label": "apple",
        "point": [
            216.89999389648438,
            47.099998474121094
        ],
        "radius": 3.1017158031463623
    },
    {
        "label": "apple",
        "point": [
            28.0,
            43.5
        ],
        "radius": 9.12424373626709
    },
    {
        "label": "apple",
        "point": [
            68.27777862548828,
            43.72222137451172
        ],
        "radius": 3.221362829208374
    },
    {
        "label": "apple",
        "point": [
            41.0,
            43.0
        ],
        "radius": 2.8285269737243652
    },
    {
        "label": "apple",
        "point": [
            196.0,
            45.0
        ],
        "radius": 10.295730590820312
    },
    {
        "label": "apple",
        "point": [
            243.91378784179688,
            42.25862121582031
        ],
        "radius": 4.742265701293945
    },
    {
        "label": "apple",
        "point": [
            213.14706420898438,
            38.235294342041016
        ],
        "radius": 3.8602135181427
    },
    {
        "label": "apple",
        "point": [
            169.71212768554688,
            45.287879943847656
        ],
        "radius": 11.805937767028809
    },
    {
        "label": "apple",
        "point": [
            268.5,
            36.5
        ],
        "radius": 1.581238865852356
    },
    {
        "label": "apple",
        "point": [
            259.5,
            40.0
        ],
        "radius": 9.013978004455566
    },
    {
        "label": "apple",
        "point": [
            222.0,
            38.5
        ],
        "radius": 3.6401548385620117
    },
    {
        "label": "apple",
        "point": [
            59.83333206176758,
            41.16666793823242
        ],
        "radius": 6.932310581207275
    },
    {
        "label": "apple",
        "point": [
            38.119049072265625,
            34.595237731933594
        ],
        "radius": 3.2052886486053467
    },
    {
        "label": "apple",
        "point": [
            15.5,
            33.0
        ],
        "radius": 5.590270042419434
    },
    {
        "label": "apple",
        "point": [
            239.35714721679688,
            33.64285659790039
        ],
        "radius": 2.7200145721435547
    },
    {
        "label": "apple",
        "point": [
            202.0,
            31.5
        ],
        "radius": 1.1181340217590332
    },
    {
        "label": "apple",
        "point": [
            108.0,
            31.0
        ],
        "radius": 1.000100016593933
    },
    {
        "label": "apple",
        "point": [
            49.730770111083984,
            33.96154022216797
        ],
        "radius": 3.050464153289795
    },
    {
        "label": "apple",
        "point": [
            46.0,
            31.5
        ],
        "radius": 1.1181340217590332
    },
    {
        "label": "apple",
        "point": [
            88.07142639160156,
            39.07143020629883
        ],
        "radius": 9.118929862976074
    },
    {
        "label": "apple",
        "point": [
            188.0,
            34.5
        ],
        "radius": 8.381627082824707
    },
    {
        "label": "apple",
        "point": [
            6.5,
            30.0
        ],
        "radius": 2.5000998973846436
    },
    {
        "label": "apple",
        "point": [
            229.5,
            30.5
        ],
        "radius": 2.549609661102295
    },
    {
        "label": "apple",
        "point": [
            46.0,
            28.5
        ],
        "radius": 1.1181340217590332
    },
    {
        "label": "apple",
        "point": [
            253.5,
            30.0
        ],
        "radius": 3.0414812564849854
    },
    {
        "label": "apple",
        "point": [
            73.5,
            28.0
        ],
        "radius": 1.1181340217590332
    },
    {
        "label": "apple",
        "point": [
            264.5,
            27.5
        ],
        "radius": 2.12142014503479
    },
    {
        "label": "apple",
        "point": [
            99.5,
            32.5
        ],
        "radius": 7.905794143676758
    },
    {
        "label": "apple",
        "point": [
            91.5,
            26.0
        ],
        "radius": 1.1181340217590332
    },
    {
        "label": "apple",
        "point": [
            83.75,
            24.75
        ],
        "radius": 3.2597010135650635
    },
    {
        "label": "apple",
        "point": [
            266.0,
            22.5
        ],
        "radius": 3.3542017936706543
    },
    {
        "label": "apple",
        "point": [
            238.7857208251953,
            23.214284896850586
        ],
        "radius": 2.525475025177002
    },
    {
        "label": "apple",
        "point": [
            214.5,
            27.0
        ],
        "radius": 12.54003620147705
    },
    {
        "label": "apple",
        "point": [
            194.59677124023438,
            22.532258987426758
        ],
        "radius": 5.61638879776001
    },
    {
        "label": "apple",
        "point": [
            42.0,
            22.0
        ],
        "radius": 1.000100016593933
    },
    {
        "label": "apple",
        "point": [
            204.5,
            21.16666603088379
        ],
        "radius": 1.9003920555114746
    },
    {
        "label": "apple",
        "point": [
            95.5,
            22.5
        ],
        "radius": 2.9155757427215576
    },
    {
        "label": "apple",
        "point": [
            218.5,
            19.5
        ],
        "radius": 1.581238865852356
    },
    {
        "label": "apple",
        "point": [
            255.5,
            22.0
        ],
        "radius": 5.02503776550293
    },
    {
        "label": "apple",
        "point": [
            85.0,
            18.5
        ],
        "radius": 1.8028756380081177
    },
    {
        "label": "apple",
        "point": [
            22.0,
            21.0
        ],
        "radius": 4.472236156463623
    },
    {
        "label": "apple",
        "point": [
            4.0,
            19.0
        ],
        "radius": 3.1623775959014893
    },
    {
        "label": "apple",
        "point": [
            234.0,
            16.5
        ],
        "radius": 1.1181340217590332
    },
    {
        "label": "apple",
        "point": [
            207.0,
            17.0
        ],
        "radius": 1.414313554763794
    },
    {
        "label": "apple",
        "point": [
            107.5,
            23.5
        ],
        "radius": 8.514793395996094
    },
    {
        "label": "apple",
        "point": [
            200.5,
            17.0
        ],
        "radius": 3.5000998973846436
    },
    {
        "label": "apple",
        "point": [
            79.86363983154297,
            16.409090042114258
        ],
        "radius": 3.1916401386260986
    },
    {
        "label": "apple",
        "point": [
            90.0,
            14.0
        ],
        "radius": 2.2361679077148438
    },
    {
        "label": "apple",
        "point": [
            63.5,
            14.5
        ],
        "radius": 2.9155757427215576
    },
    {
        "label": "apple",
        "point": [
            38.5,
            13.0
        ],
        "radius": 1.1181340217590332
    },
    {
        "label": "apple",
        "point": [
            148.0,
            11.75
        ],
        "radius": 2.0156643390655518
    },
    {
        "label": "apple",
        "point": [
            238.40908813476562,
            9.863636016845703
        ],
        "radius": 3.191645622253418
    },
    {
        "label": "apple",
        "point": [
            233.0,
            10.0
        ],
        "radius": 3.1623775959014893
    },
    {
        "label": "apple",
        "point": [
            107.0,
            8.0
        ],
        "radius": 1.414313554763794
    },
    {
        "label": "apple",
        "point": [
            4.0,
            11.0
        ],
        "radius": 5.656954288482666
    },
    {
        "label": "apple",
        "point": [
            95.0,
            9.0
        ],
        "radius": 4.242740631103516
    },
    {
        "label": "apple",
        "point": [
            254.0,
            6.0
        ],
        "radius": 1.414313554763794
    },
    {
        "label": "apple",
        "point": [
            78.0,
            10.0
        ],
        "radius": 9.434081077575684
    },
    {
        "label": "apple",
        "point": [
            63.099998474121094,
            6.099999904632568
        ],
        "radius": 2.102480173110962
    },
    {
        "label": "apple",
        "point": [
            83.0,
            4.5
        ],
        "radius": 4.031229019165039
    },
    {
        "label": "apple",
        "point": [
            267.0,
            1.0
        ],
        "radius": 1.414313554763794
    },
    {
        "label": "apple",
        "point": [
            254.0,
            2.0
        ],
        "radius": 4.472236156463623
    },
    {
        "label": "apple",
        "point": [
            183.7857208251953,
            8.428571701049805
        ],
        "radius": 13.688499450683594
    },
    {
        "label": "apple",
        "point": [
            161.5,
            15.0
        ],
        "radius": 15.07491397857666
    },
    {
        "label": "apple",
        "point": [
            6.5,
            1.0
        ],
        "radius": 1.1181340217590332
    }
]