[
    {
        "label": "apple",
        "point": [
            250.0,
            184.0
        ],
        "radius": 1.000100016593933
    },
    {
        "label": "apple",
        "point": [
            266.0,
            183.5
        ],
        "radius": 2.061652660369873
    },
    {
        "label": "apple",
        "point": [
            127.0,
            184.0
        ],
        "radius": 2.0000998973846436
    },
    {
        "label": "apple",
        "point": [
            168.5,
            183.0
        ],
        "radius": 1.1181340217590332
    },
    {
        "label": "apple",
        "point": [
            252.0,
            179.5
        ],
        "radius": 1.1181340217590332
    },
    {
        "label": "apple",
        "point": [
            249.0,
            177.5
        ],
        "radius": 1.1181340217590332
    },
    {
        "label": "apple",
        "point": [
            164.0,
            177.5
        ],
        "radius": 4.031229019165039
    },
    {
        "label": "apple",
        "point": [
            51.5,
            177.0
        ],
        "radius": 1.500100016593933
    },
    {
        "label": "apple",
        "point": [
            115.0,
            174.0
        ],
        "radius": 1.000100016593933
    },
    {
        "label": "apple",
        "point": [
            266.5,
            173.5
        ],
        "radius": 1.581238865852356
    },
    {
        "label": "apple",
        "point": [
            208.5,
            169.0
        ],
        "radius": 4.609872341156006
    },
    {
        "label": "apple",
        "point": [
            32.75,
            167.25
        ],
        "radius": 1.7678669691085815
    },
    {
        "label": "apple",
        "point": [
            27.866071701049805,
            176.0
        ],
        "radius": 28.99178695678711
    },
    {
        "label": "apple",
        "point": [
            241.78192138671875,
            169.88829040527344
        ],
        "radius": 27.653656005859375
    },
    {
        "label": "apple",
        "point": [
            31.5,
            163.0
        ],
        "radius": 1.8028756380081177
    },
    {
        "label": "apple",
        "point": [
            24.0,
            162.5
        ],
        "radius": 2.061652660369873
    },
    {
        "label": "apple",
        "point": [
            2.0,
            163.0
        ],
        "radius": 2.2361679077148438
    },
    {
        "label": "apple",
        "point": [
            229.0,
            161.5
        ],
        "radius": 1.1181340217590332
    },
    {
        "label": "apple",
        "point": [
            249.5,
            160.5
        ],
        "radius": 1.581238865852356
    },
    {
        "label": "apple",
        "point": [
            242.0,
            158.5
        ],
        "radius": 1.1181340217590332
    },
    {
        "label": "apple",
        "point": [
            212.0,
            157.5
        ],
        "radius": 1.1181340217590332
    },
    {
        "label": "apple",
        "point": [
            240.0,
            156.0
        ],
        "radius": 1.000100016593933
    },
    {
        "label": "apple",
        "point": [
            253.5,
            157.0
        ],
        "radius": 9.013978004455566
    },
    {
        "label": "apple",
        "point": [
            26.0,
            153.5
        ],
        "radius": 5.02503776550293
    },
    {
        "label": "apple",
        "point": [
            38.0,
            153.0
        ],
        "radius": 4.472236156463623
    },
    {
        "label": "apple",
        "point": [
            234.1666717529297,
            149.5
        ],
        "radius": 1.9003875255584717
    },
    {
        "label": "apple",
        "point": [
            2.5,
            148.0
        ],
        "radius": 1.1181340217590332
    },
    {
        "label": "apple",
        "point": [
            51.5,
            145.0
        ],
        "radius": 1.8028756380081177
    },
    {
        "label": "apple",
        "point": [
            205.0,
            143.0
        ],
        "radius": 1.000100016593933
    },
    {
        "label": "apple",
        "point": [
            60.5,
            144.5
        ],
        "radius": 1.581238865852356
    },
    {
        "label": "apple",
        "point": [
            236.0,
            142.0
        ],
        "radius": 3.1623775959014893
    },
    {
        "label": "apple",
        "point": [
            208.0,
            141.0
        ],
        "radius": 1.000100016593933
    },
    {
        "label": "apple",
        "point": [
            16.39090919494629,
            144.21636962890625
        ],
        "radius": 15.710766792297363
    },
    {
        "label": "apple",
        "point": [
            267.0,
            134.5
        ],
        "radius": 2.061652660369873
    },
    {
        "label": "apple",
        "point": [
            258.5154113769531,
            147.53236389160156
        ],
        "radius": 16.47235107421875
    },
    {
        "label": "apple",
        "point": [
            268.0,
            131.0
        ],
        "radius": 1.000100016593933
    },
    {
        "label": "apple",
        "point": [
            16.0,
            120.5
        ],
        "radius": 1.1181340217590332
    },
    {
        "label": "apple",
        "point": [
            205.22093200683594,
            125.11627960205078
        ],
        "radius": 6.5071258544921875
    },
    {
        "label": "apple",
        "point": [
            2.0,
            90.0
        ],
        "radius": 1.000100016593933
    },
    {
        "label": "apple",
        "point": [
            242.5,
            86.5
        ],
        "radius": 2.12142014503479
    },
    {
        "label": "apple",
        "point": [
            232.5,
            87.5
        ],
        "radius": 6.96429443359375
    },
    {
        "label": "apple",
        "point": [
            12.0,
            75.5
        ],
        "radius": 12.093486785888672
    },
    {
        "label": "apple",
        "point": [
            23.15217399597168,
            71.58695983886719
        ],
        "radius": 3.1792185306549072
    },
    {
        "label": "apple",
        "point": [
            20.0,
            67.5
        ],
        "radius": 3.0414812564849854
    },
    {
        "label": "apple",
        "point": [
            2.0,
            63.0
        ],
        "radius": 2.0000998973846436
    },
    {
        "label": "apple",
        "point": [
            40.0,
            59.0
        ],
        "radius": 2.0000998973846436
    },
    {
        "label": "apple",
        "point": [
            1.0,
            60.25
        ],
        "radius": 1.250100016593933
    },
    {
        "label": "apple",
        "point": [
            241.0,
            16.0
        ],
        "radius": 1.000100016593933
    },
    {
        "label": "apple",
        "point": [
            237.5,
            13.5
        ],
        "radius": 6.041623115539551
    },
    {
        "label": "apple",
        "point": [
            44.5,
            6.0
        ],
        "radius": 9.708344459533691
    },
    {
        "label": "apple",
        "point": [
            134.5,
            66.0
        ],
        "radius": 149.82083129882812
    }
]